huygens/__init__.py
huygens/argv.py
huygens/back.py
huygens/base.py
huygens/box.py
huygens/cell.py
huygens/diagram.py
huygens/flatten.py
huygens/live.py
huygens/loadsvg.py
huygens/namespace.py
huygens/pov.py
huygens/sat.py
huygens/text.py
huygens/tool.py
huygens/turtle.py
huygens/variable.py
huygens/doc/__init__.py
huygens/doc/mkdoc.py
huygens/doc/run_tests.py
huygens/doc/test.py
huygens/doc/test_box.py
huygens/doc/test_canvas.py
huygens/doc/test_diagram.py
huygens/doc/test_sat.py
huygens/doc/test_text.py
huygens/doc/test_turtle.py
huygens/front/__init__.py
huygens/old/__init__.py
huygens/old/argv.py
huygens/old/back.py
huygens/old/back_point.py
huygens/old/base.py
huygens/old/box.py
huygens/old/cell.py
huygens/old/diagram.py
huygens/old/flatten.py
huygens/old/live.py
huygens/old/loadsvg.py
huygens/old/namespace.py
huygens/old/pov.py
huygens/old/sat.py
huygens/old/text.py
huygens/old/tool.py
huygens/old/turtle.py
huygens/old/variable.py
huygens/old/old/__init__.py
huygens/old/old/argv.py
huygens/old/old/back.py
huygens/old/old/back_point.py
huygens/old/old/base.py
huygens/old/old/box.py
huygens/old/old/diagram.py
huygens/old/old/flatten.py
huygens/old/old/front.py
huygens/old/old/loadsvg.py
huygens/old/old/pov.py
huygens/old/old/sat.py
huygens/old/old/text.py
huygens/old/old/turtle.py
huygens/old/old/old/__init__.py
huygens/old/old/old/argv.py
huygens/old/old/old/back.py
huygens/old/old/old/base.py
huygens/old/old/old/box.py
huygens/old/old/old/diagram.py
huygens/old/old/old/flatten.py
huygens/old/old/old/front.py
huygens/old/old/old/loadsvg.py
huygens/old/old/old/pov.py
huygens/old/old/old/sat.py
huygens/old/old/old/text.py
huygens/old/old/old/turtle.py
huygens/wiggle/__init__.py
huygens/wiggle/cell.py
huygens/wiggle/shapes.py
huygens-0.0.1.dist-info/LICENSE
huygens-0.0.1.dist-info/METADATA
huygens-0.0.1.dist-info/WHEEL
huygens-0.0.1.dist-info/top_level.txt
huygens-0.0.1.dist-info/RECORD
