Metadata-Version: 2.1
Name: huygens
Version: 0.0.1
Summary: compositional vector graphics
Home-page: https://github.com/punkdit/huygens
Author: Simon Burton
Author-email: Simon Burton <simon@arrowtheory.com>
Project-URL: Homepage, https://github.com/punkdit/huygens
Project-URL: Bug Tracker, https://github.com/punkdit/huygens/issues
Classifier: Programming Language :: Python :: 3
Classifier: License :: OSI Approved :: GNU General Public License v3 (GPLv3)
Classifier: Operating System :: OS Independent
Requires-Python: >=3.5
License-File: LICENSE
